odoo/addons/stock_move_consu_location_from_putaway/README.rst
odoo/addons/stock_move_consu_location_from_putaway/__init__.py
odoo/addons/stock_move_consu_location_from_putaway/__manifest__.py
odoo/addons/stock_move_consu_location_from_putaway/i18n/it.po
odoo/addons/stock_move_consu_location_from_putaway/i18n/stock_move_consu_location_from_putaway.pot
odoo/addons/stock_move_consu_location_from_putaway/models/__init__.py
odoo/addons/stock_move_consu_location_from_putaway/models/stock_move.py
odoo/addons/stock_move_consu_location_from_putaway/readme/CONTRIBUTORS.rst
odoo/addons/stock_move_consu_location_from_putaway/readme/DESCRIPTION.rst
odoo/addons/stock_move_consu_location_from_putaway/static/description/icon.png
odoo/addons/stock_move_consu_location_from_putaway/static/description/index.html
odoo/addons/stock_move_consu_location_from_putaway/tests/__init__.py
odoo/addons/stock_move_consu_location_from_putaway/tests/test_consumable_move_location.py
odoo_addon_stock_move_consu_location_from_putaway-15.0.1.0.0.6.dist-info/METADATA
odoo_addon_stock_move_consu_location_from_putaway-15.0.1.0.0.6.dist-info/WHEEL
odoo_addon_stock_move_consu_location_from_putaway-15.0.1.0.0.6.dist-info/top_level.txt
odoo_addon_stock_move_consu_location_from_putaway-15.0.1.0.0.6.dist-info/RECORD
